DeCGR-1.1.18.data/scripts/DeCGR
DeCGR-1.1.18.data/scripts/DeCGR_windows.bat
DeCGR-1.1.18.data/scripts/DeCGR_windows.py
decgr/DetermineFragment.py
decgr/__init__.py
decgr/correct.py
decgr/mainplot.jpg
decgr/plot_SV_region.py
decgr/plot_reconstruct_map.py
decgr/runHiSV.py
decgr/simuProcess.py
decgr/utils.py
decgr/cnv/__init__.py
decgr/cnv/correctcnv.py
decgr/cnv/loadcnv.py
decgr/cnv/runcnv.py
decgr/cnv/segcnv.py
decgr/cnv/util.py
decgr/fithic/HiCPro2FitHiC.py
decgr/fithic/__init__.py
decgr/fithic/fithic_copy.py
decgr/fithic/myStats.py
decgr/fithic/myUtils.py
DeCGR-1.1.18.dist-info/LICENSE
DeCGR-1.1.18.dist-info/METADATA
DeCGR-1.1.18.dist-info/WHEEL
DeCGR-1.1.18.dist-info/top_level.txt
DeCGR-1.1.18.dist-info/RECORD
